{
"4mohzvmxapx7glrvi5jow7rt":["dhstom","Doug Hill is Doing Okay!"],
"evwlyafjoiqqgbsypzbq62i4":["dhsanders","Thag Simmons"],
"p3azakfnbnhhu6wpmsygea67":["dhsauno","celestial korean being"],
"s5iaa3o3mofawdeyromuf7dp":["dhsmith","Doobie-doo"],
"l5nt42rbk5ycgteobfjiwa6c":["dhs","Department of Homeland Security"],
"yg2z4ib5vymn7n3rmwttmurz":["dhsung","DH Egg Sung"],
"vsvsy7uiuxupolufsrchq355":"dhs913",
"u4pgiljlcwo44k6yyc66npuu":["dhsorrowsart","DHSorrows"],
"3rwgfpvkg5cuf7j6yfbaoali":["dhskdshakjdh","꽃담"],
"e5u2n7vnideh2gywezsmhdx2":["dhseimfineart","Doug"],
"wglolu7julyp5sgie6lqpd7o":["dhspeedwagon","Free Joey Votto"],
"kweetfipnohqftg3ah5x33ag":["dhseldhorjs","온건"],
"p5tdqbdj3h7tfazkkmbi6l7p":"dhsdavis",
"4tq2tpluleujtw7ujdza3jca":["dhstein","Diana Stein"],
"nyx2wc6y6jwk4mvpv55qoo7i":"dhsynth",
"ah6kfrarwgfzn5y3gja35fml":"dhsnwnkl",
"6agci2el4psypdxwsjxvsfjw":"dhschmidt",
"ju77qmd52djf2cobxs7fwp4u":["dhsenyayo","*DH*"],
"jra3ayqp27cg3eb77d6ofkud":["dhsu","David Hsu"],
"yjah66n43uj6rwlgduhhshv2":["dhsd","daniel"],
"4xqziovf63w4v2flppxig6hd":["docnox","Matthieu dhs"]
}
