{
"kcwa45oawdosu6lurew45lra":["4thgradedropout","daka"],
"l37wjych2n36xkssxkjuq5qa":["80hzghost","dakota "],
"duutmuifudgwnrjos4ko6tdj":"a2dak",
"v4v5njwymnn7rajxlhrdwanp":["absolsama","abby (daki is live)"],
"rmmm6epxoqvkzd4vzff73alo":["acrylophenone","dakira🇺🇦"],
"lkitvxkhczyvr2apg5qed3lz":["adumbreon","Dakota/Cody"],
"p47c4toxbjttqng3gbl2p37q":["aktmr","DakochiteDragon"],
"peavbwi3whsjv5nsk2zfwvg3":["aldrendakeer","Aldren Dakeer 🍁"],
"k4a3bppbc2odriqpll72otno":["andydakin","Andy Dakin"],
"rh44odbibww45sphk6wv5cc6":["aosthene812","Dakota 🐌"],
"t2skujh2cb25marpagv2cjdj":["arcaninedakota","Dakota"],
"o2s7bamxspglm4cnxnw2ey6m":["artbydakotadrake","Dakota Drake"],
"7sf7hlyd3unk5pvdz7zr2itx":["astrotone","Dakota Kitzman"],
"ees4eyxcs4g6egybbbpq7f77":["ayimeart","Ayime No Daku ✨️🌈"],
"d2rvtrmjtyw654u45kbrn7uz":["bayat","Dakhoo"],
"3mjycsg76lfkqm4opgebium2":["balco","Dakaa"],
"wt7hziu5xouaug5vhpitpc4o":["bangabear","Dakuma"],
"jdbjgxnz34cgijimup5k4uzq":["baelor4","Dakota Garcia"],
"3b4bhz7nlovratbuo7gsxihy":["bearboobs","Dakka"],
"ipg6zhpkgoqmsat6t6xf6lfb":["bigdakota","Dakoters"],
"l3psfvwucd4yto43df5zx6j4":["bigdakenergy","dakota "],
"rwt5fybdqswr7koruj663n2a":["bjdake","Björn Dake"],
"oxyvuh7szjako5xkhp4dgfym":["bothdakotas","dakota"],
"cxakkvghevhjimcqzzbo4ndv":["dakanektr","Fio Pleas Out"],
"2jiko2vjzz2dhjx57ujmodzu":["chaosmanaged626","Dakota"],
"gcvsnibxghwi2obuwvuzqxkl":["cintrondw","Dakota W. Cintron"],
"2lcutclblejyypzi5pd64h4b":["clustercrushed","💫 Dakoda💫"],
"jkh4oznl6zro77ibs7qbkl2z":["copycatjoker","Dakota Hilton"],
"mwgdgblugozoosd4ctziixwr":["coachdakota","Coach Dakota💪🔞"],
"3cqtz327jkhyj3vewiyhmsvw":["dakkireads","Dakki Reads"],
"6iq5h33c7wsniesxnv7oi4gg":["dakotahpxxx","Dakotah Porter"],
"7ek23ccy3dm6gm2uiq7izz6c":["dakkar","Dakkar"],
"7s77ksubdlv3tyey3hye5epx":"dakhil1996nsfw",
"cngbbyez2ps6kxrmqbs7hldc":["dakotabones","dakota"],
"ct7j32rioagu2y6qpwpl6k5n":["dakharding","𝘿𝘼𝙆 𝙃𝘼𝙍𝘿𝙄𝙉𝙂"],
"dkyjw6yoqem65vxislehwcsj":["dakooftacos","👻 47 Ghosts 👻"],
"dud5gzotcqk2mvwjvd2vyxu4":["dakotaisasleep","Dakota?"],
"hgkbf6rj55nctwabbydrjzta":["daknifecrow","Knife Crow"],
"i44kk2oryfr756vqat2xx7da":["daktx2","Daktx2"],
"i4y7567g6q3qkwyxic3tu5bb":["dakotaschmidt","Dakota Schmidt"],
"ir3o52e3o66k4kib2zbuma7e":["dakas","Dakasr"],
"jzvheejrlsnln5nuvodugfn7":["dakotahfoxtales","I am Dakotah 🦊🐾🇨🇦🏳️‍🌈 🔜 MFF 2023?"],
"kito45me5k6a5psuate7znz5":["dakegra","Dave G"],
"o54c62g6jaq5epj2cawws52u":["dakai.gay","Dakai"],
"omsqinvf6gvpfnejs5y32edr":["daka","Rubber Pup Dakarah"],
"oqkvivcu3omv7gpxwu6ys7ev":["dakvid","David Friggens"],
"ovofx2cjqvyrqcl6bit5tred":["dakuhamku","🌊바닷속 햄쿠쿠🌊"],
"q2zcecrbldfo4eughcjsuu4q":["dakinedoggo","Dakine "],
"q475whwgqrjyfhvmpckrtr7s":["dakotabun","Dakota"],
"qngn4ojj3wqwdreq54jnp4we":["daki","DAKÍ"],
"rmapgp3q3dnfozbgl6ouysmc":["daks","Daks"],
"sc7qoor2azgibwht7dfmncku":["dakota","Dakota"],
"sqfv6djllvqjjssby6pqbjge":["dakotasilver","Dakota Silver 🔜 MFF"],
"vn5jzgduor5ezwdc4rb4f54b":["dakiberry","다키"],
"piswk46uuf4lsb2ms7lu2b76":["dak","Dean. "],
"xbmhyi23enjqhipgdrryaoyu":["dakcar","Daniel Akle"],
"zy72oqirtlzshg6biujlclxp":["dakotah","Dakotah Cote"],
"kou7ykd6hzsi5o4eawpyxnmo":["dak.dev","Dak"],
"vypl5fbwjikrf76h3gbr7eom":["dakshin","Dakshin Adyanthaya"],
"lu3ddh2o4siy3l32kgo5r4ol":["dakwrestleford","Dakota Blueskyford"],
"6kclchxbhqx2ttw6csgkv2ie":"dakinita",
"nlawbkkrw5gwqpr7koifxprj":["dakacki","rand0h"],
"cb3pkkhs56ri3qkhrlu4hau4":["dakotamaker","Dakota"],
"x2wsmkhk27car6wco3ycreev":"dakotasmith",
"zq2u77fclxamkgfgquduo4li":["daking","Daniel King"],
"ijmf6f7bkvaeqnoxreo4e3oa":["dakatsuka","dakatsuka"],
"emedpiiizprdv3nuaoerjz7a":["daksh","Daksh"],
"4dsluoqhbvukhq6k3czqusya":["dakekang","Dake Kang"],
"mxm2yfmn4psgwuznbuidtf5b":["dakotabrown","Writer Dakota Brown"],
"du7mzpdocbz5kt62dvxn3qw5":["dakineman","Chris O"],
"cr3smlx2wchncz3tnkwos32j":"dakisdead",
"n6kaufwoz3sr7yu25f2gv646":["daksahoy","Dak"],
"zxk6pmdqlpdq6op6an4kxiwg":["dakool","dakool"],
"q42lxlloyalctyh3kyno6qfv":"dakotanardi",
"brqftlbwa2obstxo7fy52w3n":"dakotagrabowski",
"cedcym5ikfcpk3vxejv6t4vj":"dakief",
"xn26nuvzxrzbb5og5d3p7wts":["daktilo1984","Daktilo1984"],
"prnmv3litg5sm2f5offf6ydb":["dakotasrare","ju"],
"g6oti6cs4vp2uszvvwcuoxai":["dakotateach5","Jody Erickson"],
"4xlturlei35cnb42yiv2jzjq":["dakeri","Dakeri"],
"fe5d2y4jjnx5wz4g5tmy5pxn":["dakotawright","Dakota Wright"],
"xadbtbuomzj6wmbcsdrw5fy3":["dakotacurryart","Dakota Curry"],
"o6txfywotjmfm5tvqv2q5gut":"dakejavey",
"vh57jqnpyvj2rqxwmtcaaeba":["dakotafloyd","Dakota "],
"nr7lgb47rplvphmsjebdus5w":["dakeller79","Andy Keller"],
"5oy2jpcubbofvr2susaj67vz":["dakdread","DakDread"],
"nnptoern3medoa4zf6poocaw":["dakhil","Dakhil"],
"53tf5mlvnnji3wcejsu5my7t":"dakki",
"xexxrbqugl3vasohm2fv6y3u":["dakupoguy","crunchy"],
"a2i3s622jebuyd7xdyn47sqv":["dakurooo","だくろー"],
"l5uuyrrqry7g5owa27vzdsz4":["dakotamacdoodle","Dakota DeGarmo"],
"kz5zuug7y6i6kwvmle64mim2":["dakejp","28 Dakes Later"],
"yyyop76msdcrqdrz27mwlazq":"dakyo",
"h64snfzbtpjjffqtvu3rusul":["daki-qi","DAKi"],
"lgtqf435zcdohumgp4ikh6t4":"dakshan",
"ylthroyabj2u6ttaeqalmfl5":["dakishambada","Davy A Sundquist"],
"3xxizk7yy7b6evrbutjhvdad":["dakotawolf12","Springs (Kota Winter)"],
"guhy7hmogu7qa3ye2pnmpan2":"dakath",
"owsz5nzjaqb25rciab3rrbgw":["dakuro","Master Dakuro, χblade wielder"],
"adup4ww6gfepwnum5zwr23fb":"dakopt",
"5grptmcwqazdthvkxciehrak":["dadadak","DaDaDak"],
"pxo5dnar6nrx3apb2rnimn5k":["dakotaindc","Dakota"],
"xy6az7rt7vwilvwth62dq2ic":["dakotaraine","🏴𝙲𝚘𝚖𝚛𝚊𝚍𝚎.𝙳𝚊𝚔𝚘𝚝𝚊☭"],
"wxtmu2ph2hieckj64wotkmkt":"dakarrally",
"u35y3ciozkveklpoqmzgxph6":"dakotacx",
"ewvbmgjixgvqlcudsthgeyh5":["dakoop","David Koop"],
"ym4shswle2qo4nlrgfn6pmlk":"dakito",
"rjxmkc6w72f5rkefbzf2opbt":"dakoda",
"vrfodv4ejydqumjoghyoynw5":"daktor",
"d553wk4ae7kjszg537z2nejy":["dakotathemoose","dakotathemoose"],
"454xozhn7pyvfujojth3tw7f":["dakotag","Dakota"],
"hzab2tzb2rupvfhjpunyx6dr":"dakotafleck",
"ubqii57knafhakdivdcyz2bu":["dak0ta","dakota"],
"uixd5hebagha52dsgq7w74m2":"dakotarob",
"sbmy6m2twe2tkfufif4cafaw":["dakotabusby","Dakota Busby"],
"yqndt4heaurjefsrcd3y6muy":["dakaya","dakaya"],
"fa7jrkda2ml2ndhmgbfuds3s":["dakotaraptor","Dakotaraptor"],
"zb76s7pbdzrnvy7uu6susrjl":["dakira","Matthias Niess"],
"uo4mwlwtbbzpvktxzal4nkan":["dakotarandallart","Dakota Randall"],
"jdkyefuxofagw5deeopk5kxf":["dakaire","Noe"],
"pwfxihpm4c5jhenukdqng6lv":["dakeus","-ˏ` dakeus ˊˎ- "],
"xuzdlxjhjwsifrrm4n5g7ij2":["dakotapaw","Dakota Paw"],
"6lbygkgvxojuvcckjgzfhhh7":"dakotablackman",
"ewhnn4ep52qek2trpgn6dvot":"dakduffyj42",
"lyjraw57mvpuqjskljxvdcgx":["dakleinbot","Dave Babbott-Klein"],
"24rkzseyaarlpztl6i2jneao":["dako","Dakó🇺🇦🏳️‍⚧️🏳️‍🌈🏴🚅"],
"ry4qqtfd3bbzft2ibxrsdlid":"dakotawolfy",
"u55wblrkjal6cedyiqkzchv5":["dakskihedron","Nathan"],
"b4orhua7ophvgjv3wdqucuwp":["dako243","David Dingman"],
"rm5mwzydphbpfigqk6ato5qt":"dakotacarroll",
"tv4wycnplpn26uzkdw5fui4k":["daktangle","Dak"],
"2sisjjqnaykkyi3a5msxkhq4":["dakkster","dakkster"],
"ikbpybnkhu7v5i2rqh7xf562":["dakes","Dakes"],
"mx3ytk7lauo4zbfnerw57siv":"dakoty0",
"kdiyxyfjf2ft4z7i3dpihg34":"daki029",
"rp6dvba7ycfzcc6hqriduhom":"dakergds",
"ex5nrt3mnp4valb5w5omfcv2":"dakshshah",
"akrjtvgyjmwulypoq4g23ktq":"dakikaveskor",
"rgqp6gveden3gblwc7lo7jci":["dakotadrox","Dakota Drox"],
"gw3gqeac6di577ugg4hqmd3p":"dakoteeeers",
"cjjesjejpov2yintpda5jz3k":"dakgalbi",
"j5u4olzszgwzcpnoiam33lo3":"dakotaavery",
"tyaixm7xhgbsfxcpj7nqcler":["dakuwithchaku","Munna"],
"kqfnnd2vxf7fxnr5r7rgcrgk":["dakotawoofer","Dakota ➡️ BLFC"],
"einsxord4ibfl4w6u43ku6d5":["dakhgame","tantao"],
"fdiynqezzdkrhphoys3opzhu":["dakanodragon","Dakano"],
"2zhbjpgqybazkgpagkianid7":["dayco","Dakota"],
"xi23fgbony4zr45nsrgusulz":["dakotabreelive","Dakota"],
"onzypbglpbdhyyjpe2bdjrke":["dakkawoof","Dakka"],
"t4yzfa6eva4kion2bqcqaasi":["dakota-wolf","Dakota 💙"],
"bevtjrpoqql7jfvd7wsl56ml":"daktales",
"faoxvhk6mscv7f5cemktnvwu":["dakini","simsim"],
"6cthdf6r5rfz4x6uxwmzzbzk":["dakimchi","Leon ★ Da Kimchi"],
"psiz3a67hvnoxcdhkuvtmv6l":["dakkydracota","Dakky"],
"xotf562mrzmw2sf4cjr4rq35":"dakvlnk",
"vnuxdnuknmwpa7tkfgkfhcfp":["dakoiart","Dakoi"],
"yz2xsuesmzr6td5ybpxtj2fg":["dakkumauji","dakkumauji"],
"hkw5uu64ylljlg42m2gltcvi":["dako2117","dako"],
"zokgziejqpvpnhrjqqjvb77y":["dakotaheeler","Dakota Heeler🔜Furpoc "],
"jkoj6q6j4rgkdya42zpxql4y":"dakkadax",
"pboo4ngqvwbm7tyldmm32sqb":["dakky","Dakota"],
"lpsggiu7imanzz4dy66a4ddp":["dakar","dakar ツ"],
"rm6zbevgmnbhektzwoegz26w":"dakshi",
"r5aqnldy3lvilzen5jfjtad4":"dak609",
"3mzs43fx62fmoftqj5bhbkic":["dake","Dake"],
"mo543u2cblhajlybixe3pn5q":["dakhanavar","Dakhanavar"],
"ngyy5hhhdbnbd3tvrrmu6d2h":["dakotad","Dakota"],
"5nchvcgwzcmy3trpvrkwerkc":"dakre",
"gc6c4gkwr3gmq47m5ed3sxzp":["dakidstephbsky","Dakidstephbsky"],
"7twnhahvygyj4k2rok757dbn":["daki4","daki4"],
"c3wu25art5abzsyfwqiq7zsx":["dakotairishie","Dakota Irish"],
"q2uazdeebdznau7pkixmosc4":"dakuwan",
"3jnebfizeiet25wqgqocvmmm":["dak7e","Dan"],
"s64pbuew4mytcvm2uwgjxklo":["dakotapup","Pup Dakota"],
"zhs5ssp7lgmgaey5x4qtq7ux":"dakazu",
"xutpt5gki6ut5z6ybrwhw2an":["dakrukru","DMKruiz"],
"ixnvyucc5qvyuy6lfrpczg4s":["dakinefarious","Daki / Jaxon"],
"zlme2xjgaoq67ciolmkjgmfw":["dakudaa","dakudaa"],
"5yxxulipcmociz2dpdday7jc":["dakerion",">//Đakedake "],
"sj3xembrstu54fgjjqhgkt6v":["daktoathegreat","Daktoa"],
"aditchbrcyl4ck2bn4nsb7cl":["dakotakdash","Dakota"],
"s4dcbohz5p44etpdgouzusaa":["dakotamurray","Dakota Murray"],
"cqaz6enq43jovjpdphqxnqhi":["dakumara","Daku Mara"],
"3lckbqthu7rgwknmpth5tfbi":["dakotaofthenorth","Dakota"],
"x3oauognlnh7qg6v6nvlduh2":["daktari","Gertjan"],
"azhnlvhue723xgqtgdfcyvat":"dakinwuff",
"6ux3v3hqtxy256zbdsl77opk":"dakinseesin",
"ygnvdnufz7s2wvqz5jayltot":"dakotadabearhere",
"iuplalxbcrraouhw52vbe3zt":["dakagite","Dakagite"],
"dplsq7q5qdx5d2isamiokoeq":["daktrogg","Ulises con doble T"],
"bf3o7bnsnv4dhvlylyxklo6e":["daktari1","Daktari "],
"4ei4wd72dbt537gky6fvixma":["dakkadez","Dez🐀 🏴‍☠️ All Day I dream About Shatterpoint"],
"sguph5aceodfhpxkmu3s6ow4":["dakkie","dakkie"],
"7k66x55qdjc36jkaxwxhp3ld":["dakaisuke","打開策"],
"3hfdtjrdz7yfnfmn3tbo5vra":["dakotaotter","Dakota"],
"fdtbunkhv53eaz5fqgd4444y":["daku","Daku"],
"sfrakzpxvyek6lih2m4gqyrr":["dakspiller","Mack"],
"7jev54ilow2qktsmjvwpnc4u":["dakcbomb","DaKcBomb"],
"e3gznfnbjasiwa35pdxro5nh":["dakkori","🍟"],
"xe7dsgrynxjtwqxdr7nxyi4r":"dakhath",
"2hnvpw67y2hnatylaughah77":["dakato","daka"],
"5ej36psvkikqkgyxzn52ryoc":["dakotapnw","Dakota"],
"zhot4mns7yz76jdaaw573cut":["dakotafoxxxx","Dakota"],
"ufn5h7lliklqevr7nwjjvfb4":"dakotahhitt",
"hv3a67u2jr7xyzw2a2cpt3z5":["dakko","Dakko"],
"vrn4varmf7t4cheqrofebwgt":["dakkkeomo","닥끼"],
"mwt5otygh333xg7cdtyxoenq":"daknim",
"cidvezn5usuuzejqraolshp3":["dakora.arviksa.co.uk","Dakora Baer"],
"xhgh2jkgixr3qajdniwdtptb":["dakotzichab","Christian"],
"izyia3uptgtfb25aexuwblvg":["dakuistiredart","Daku"],
"4vfgklk6mbahy72shynoxgut":"dakotalovell15",
"37ie7efssscxuqekmstabf4w":["dakotadraws","DakotaDraws"],
"qreddjadd7v4uwwaq3yasaws":"dakkath",
"5gvliha52mzpdopabfqvkvzd":["dakkydraws","Dakky "],
"55z5hxoaks65xyi5gxq2vvpr":"dakotalovell6",
"ekym5fbdj6cegdh6gocllvi7":"dakotablue",
"qsn4ttsjw5kjyp64kmwoywia":["dakotaastrowolf","Dakota Astrowolf"],
"k2i5szm3vonaee7wmx3qxpb7":["dakacko","Dakacko"],
"lcmkol5ijkaancbz7faunva6":"daklute",
"w7qgl2z3jj4f4cu6ll7ievbg":["dakotahorse","Dakota Fieldrunner"],
"gzlnx3tnjbkfxstvttfr4v73":["dakishimete5896","진저에일"],
"w6lu44t4jfnbnrij4lfvgfo4":["dakuraigun","Raizeth of the Many"],
"da7i5jqorvmu6as3qalxhtb6":["dakismyqb1","Wendy"],
"wfixv367qzttldheispdgocb":["dakotabou","Dakota Bou"],
"b6ocfeobgst5tkrzxskcpkgs":["daken13","駄犬"],
"yzt5r6l6ky7defnr5k4kzna2":["dakan","dakan"],
"t3gkron2bcbfutophpibwsql":["dakoma","DaKoma"],
"o26jrppm3po3ysqdkr35kdhw":["dakotaswinski","Ido Nowski"],
"sm7vhuyxzofz6ea3hrsll2s6":"dakon",
"g5cjbv75uggc5qxekzsggixw":["dakiii","Dakiii"],
"kqturtmvhzl2mmrpia73bcqn":"daksondeck",
"jnp7s7kqmgkeqrkmo6r3qcyk":["dak1117","Dakota Eleven 17"],
"afvv2pxd6evttkqzqqoafn53":["dakotacityrag","Ashanti Mills"],
"t4mflclhpdaspimzklygwcl7":["dakotasaurus","Dakota"],
"afgl6ifakne5eiinh4qebgzp":["dakliz-taru","樽"],
"yz3dxwedoslwldlu4ltdyh6u":["dakotaplays06","DakotaPlays06"],
"2zjn7ypcwcemtfkaoxe6im2l":["daki674","DaKi"],
"jxvdbjzr7hzfspxsabv5dkro":["dakoru","Dakoru"],
"xvs3wjkucphrgk6payqbofzr":["dakotasievert","Dakota Sievert"],
"7jjokeqjfnpanl57r3ux2e72":["daknar","Daknar🐺 | COMMISSIONS OPEN"],
"zh5c4iejasdawdig5xiqlggm":"dakotatheraptor",
"gwra26fobtzsrsmp5yvjy54n":["dakodragon","Dako"],
"hbumrhdnkkrkvy3vriwdtx2k":["dakuru","dakuru 👀"],
"i7ub7pvq52vhmnjwwsldikfz":["dakotalogy","Dakotalogy"],
"r5h6n7hjrflpvkitkarhe6y6":["dakoten","Dako"],
"jthizqthzjlywljeyjji335e":["dakokota","Dako •⩊•\n"],
"xqp7wbhb57wa7yyyaztgr7qq":["dakotaaa","SAMMY"],
"6spzf5xrl5koytpdu6rfnema":["dakoval","DakovaL"],
"ivrly6gfx25lktci3einbv75":"daksch",
"ee4blqffwfunv6ykln2d2wsx":"dakotawolfy25",
"ph34nkxombf3v3gdkv7hkt6t":"dakewlguy",
"ntgc53cjodipmmvrhlfhr3go":["dakoindasky","Dako"],
"5mbjztgtzhkgxan3hwsgj4kb":"daken000",
"elpoztl5pztksehmatpcchrw":["dakotamckooted","Dakotawota (•‿•)"],
"bv6pmuihzbrlmcyypde2emmk":["dakotafoxxz","Kaitlyn! AJRmy!"],
"dyih67iasvjkcw7cxcokvfhd":"daktoii",
"fddtxsmwesa44chyaii6thg4":["dakohnooo","✿ Dakota ✿"],
"436tcfmyrx4opzq6ava5izyn":["daksha","ദkshഅ"],
"j66whkkzbevieahmotfq45gj":["daktagreen","Dakta Green"],
"2tcgssacqbin6e3exewcylsy":["dakludge","kludge"],
"qnlou5e5wrz23oqhcr3tfmbc":["dakargelb","Thomas D."],
"t5rvju5rhwh3bn4vnmgbzoau":"dakwah",
"7oskrf3n4hhmgzwg2bwhgwjf":["dakota99","Dakota"],
"j5iovs4ywznkfctdzn7zbey4":["dakitty","Thunder "],
"ohbfzhmfq54n7j6f6sd2z2mb":["dakimakkura","Daki💤"],
"a4mrdn7w265fmstx4qhootat":["dakotathesatyr","Dakotathesatyr "],
"r63juenfni5lyahm4prwvhdg":["dakota150","Dakota"],
"7aq7fdluslkvxc3dwjacorpi":["dakraus","dakraus"],
"k5ojl3damxmrwwzoezsex5z5":["dakillidan","DaKillidan"],
"dzlpjdffqenulmlba674y6oo":"dakisback",
"kbmdi3szl7xo7iyw4hnmleug":"dakrith",
"6pjnvarbuekgp4lj4mvlnj7d":["dakoitm","DaKoi_TM"],
"z7p4r3qidma2fbf6zx6x6zms":["dakotamakes","Dakota"],
"c3jn65yuhuy3iexipp7f7dck":["dak62","DAK62"],
"zdju2ezd4vqggxf32p2y3kei":"dakotahanger",
"t4yqzygxocwgrsidoycudq2w":["dakotars","Neon neo geo🏳️‍🌈"],
"6byicgrexa2iyptctlwbkfxz":["dakotathecollie","DakotaTheCollie"],
"kogfxn74awpcyebqooghoysr":["dakitkat","Daki ✩"],
"d3fvkm5m4faey4jexsuqnwbk":["dakotahh","Dakotah"],
"3nnfttrliwv4gravznv7rt7r":"dakota294413",
"u6u575ng4da5sqg6kxysos4h":["dakithawolf","Dako Bonbright"],
"hrz2akq4yrznxwgn423sp2ky":["dakshyto","Dakshyto"],
"megqp6clv3z25jo5vxalix3x":"daktalis",
"szdgmenoy42sxqd2lmx32z2j":["dakitticat","Kitti"],
"xdrg5mvqv4tboghatwqhedl3":["dakkat",":Dakkat:"],
"4ncmrebzptygqjvs67433gm2":["dakotamagic","Dakota"],
"4mm5gjdkbkwh7sc65lj2wmn2":["dakosito","Dakosito"],
"ec5o3uydodtusqy36zjdjafy":"dakoba",
"jsca54aug5s2xg63kvmmdrbe":["dakuenjeru","Daku"],
"bmpaqtrzzfvhluvw7phuo7if":["dakara","dakara"],
"2djqpanim2amz4jevyqiqpdw":["dakoraa","Probabilita"],
"uhnl4swpe2lcdtwe6r3hoj7m":["dakota79","Jackie Ivers"],
"kzqpfuhdmq3zf6y3h5a7hlrf":"dakotamallo",
"7ligqwxpujzeay3idcey53z4":["dakafinak","Daka"],
"uz5sjqm22p6jd3elv3xq5ilt":"dakoter",
"u3rypsitpy4hvmscgwcgmogp":["dakouzy","dakouzy"],
"iay4rwbos53wv6nks3c6eu7d":["dakotastomp96","🔞Da-Ghost-a Swamp96🔞"],
"uiawcdiiqvrf65qrswie6b4o":"dakotafannee",
"qg4l3ttwly5tau5d4qgwgtsc":"dakerl",
"xqnjjqqa5xdeuul346tok2jr":["dakotaisagator","Dakota"],
"f3dsdicutkimhr5cbaxmnvig":["dakiwoo","🔞Daki_woo🔞"],
"wsx5tqd5jkcf7hyzfuwrrc3n":"dakotakeck",
"jljvvple4kemx6xgw3x4wlhh":["dakn","David Krohn "],
"f7im4mixlmasproyhimj2fw4":"daknak",
"rumspezkstiwcaclbrepqiwr":["dakiyo","Duck"],
"yq33t7bvv2brlxoimzizgsyf":["dakudo","Dakudo"],
"pszy3rf2vhcpbmw74aqcpf35":["dakrfrier","Darkfire"],
"boojuqqs3cl5icmcq47u4ioq":["dakotademolition","Dakota Demolition"],
"kvoaopr6epk3la6pazqqzgnl":["dakotathefem","Dakota"],
"rx4isfpmae66jb42n7aml4pd":["dakistrafe","Johnny Silverhand"],
"ep3amxy4xsqqkcwqzwg267gj":"dakkea20",
"fje5b733eho7vnw72zny4uaz":["dakohorse","Dakota the horse"],
"itu3kla2m75am2eytlrziv4i":["dakotahfoxad","Dakotah's Naughty Bits"],
"f25wz3cosioa3emsegl7iejl":"dakkon",
"vflai3krwx6zxz4h6sani3e4":"dakree",
"y3rkt7cj2dhz3xmdvcgopsge":"dakotacwright",
"uhnbj6ko36knuqsertyb6rdq":["dakotanfutball","Dakota Roth"],
"h2olvy4o7uwmer2uecydlczl":["dakotamarjan","Dakota Daniels"],
"syl2e7i2zu5xbv3tjrapikdn":"dakingkojo",
"gbi3amv6hdrwufy34fzcad7v":"dakari",
"t44ufm6n5bxgc5e6fj2abf2s":["dakorita","Baby Kota de Nieve"],
"5xjfhryjg5nlkgdpkvxi2msj":["dakinikat","Kat Huff aka Dakinikat"],
"oz4i36apleahyyrro5lxlol7":["dakicuddles","Daki 抱き"],
"a4rwre5trj4ynbszt5riti6c":["dakuhaaz","다쿠하즈•HAAZ"],
"32smvpmsouawp3rsyfqx6uib":"dakittenz",
"5yzdddbzwb7fvuvfzklcbojw":"dak0t",
"ggo6arx46frb27b6v6pfvdwf":"daksonenko",
"632qiikqqvyrmuliy7uerscc":"dakota0451",
"x4mcg747ir3v7jokvu6xvrsj":["daken","lala"],
"p23jv4bmhkffjw6kf4wtmxvi":["dako365","Daniel Kordes"],
"xpgbv3xugjzjidecfklbtx5g":["dakotafoxtrot","Dakota Foxtrot"],
"6i5ooindjqfdlqur26c3mocz":["dakaraifluff","Dakarai"],
"52csjtvw6qquv272fbbv5oof":["dakotastarbat","Dakota Starbat "],
"phoe42gd2f4hgepq7w3sct6y":["dakuisha","Dakuisha"],
"fa2heocguiq3fs2a7xbmyvcs":"dakras",
"o3fyg5ndf3u4fmlz3rwfff6g":"dakasanctuary",
"kzfqpqgjocarbuuoqtdwe6el":["dakotamoon","Dakota"],
"v5tw5zzamhmmwpzgnayrtjlw":"dako-art",
"kydbxpc2jsrk6jl2joi2c46t":["dakooters","dakooters ❤️"],
"hdmelyn5mgriizivgedyktf7":"dakrumwiede",
"33qd6fgtjsy264ls42v2qs2o":["dakgames224","Dakgames224"],
"az3nkzcfhtikargbo5vuk2t2":["dakuuwu.space","dakuuwu"],
"cruem27bso2ab2kr73vbko3d":"dakkerdb",
"5eosvji46u3zk66qtpk3pu3j":"dakhova",
"e6fcsttozqgounjiltf5ozs7":"dakotaaaa",
"ustrjx2gqvod6v7mqbwk5hr6":["dakotabeltonart","Kota~"],
"o6ame6xdvgn2kpttsmijvo5a":["dakedobaby","Ra Weir II "],
"eje736zvo2ploct7hxujisxe":["dakotahart","Dakota Hart"],
"lmc2rkf24c4cypw2krbbhv7s":["dakoller","Daniel Koller"],
"bpvsdcx7zarg7j75ekchhkkw":["dakimaru","dakimaru"],
"wrdkfrpcvy5effzmezi5y2ox":["dakie","Dakie"],
"zfokm3hqtxw7g5l2pxwfzu7d":"dakamod",
"hbnh3alzphlll7twbbvdnu7u":["dakydakara","Dakara"],
"mfdu32z6qurdqxvezu2u65xy":"dakalo",
"b5dcj4zg4y56u46bkfgeproe":["dakudrajkierr","DakuDrajkierr"],
"2ph2zxvpuaxs37fp4mfbk6ng":["darkroxs","Dakroxs 🦊✨"],
"6nzbtzfjvb6teanomu63z2ls":"dakiwaki",
"5aqbsv44ya7shrzp23gbqzox":"dakaruh",
"ieo4acj5egmj2ifs4xje3pdk":["dakourtis","Dimitrios A. Kourtis"],
"z6wbzvzah6dkklazfbnmailg":["dakotawilddog","Dakota "],
"cyaczxnx25nmedoqftr77bjg":["dakotalovesyou","dakota"],
"kdyf4vojgddnzhwi25yykvpi":["dakkuringu","Dakku"],
"7t2xazmtghxpga36wn5jokro":"dakitti",
"5xrmrc73gp6htix2slyd4vza":["dakhran","Dakhran"],
"3wsu663dxc6fdvrrtfuw6o2a":"dakhar",
"dwso3fdf5c45wlbmrc3ggs5q":["dakpinaroglu","Deniz Akpinaroglu "],
"2t27cnrb4beartobagaj7jxj":"dakitodasho",
"goksdxhyme2ykdaardq27eru":["daky","Daky Kainy "],
"ewa2stsb4sy4vtyfzyexxnz6":["denaricus","Dakota R uwu"],
"kowy2atnwtgrgkhkvkutowxa":["demyxapollo","DAK"],
"lm5szztepcoxe7oiiu7vsibg":["djgg","Dakota G"],
"ac7ixxm56ij7oaaop6h7dn5y":["dkdelidj","dakide"],
"wo5atlq3eudud3qrk23mv4dw":["dktadc","Dakota Cammarn"],
"wazcoco2zob3ipmczvv5tvoq":["dkeldsen","David A. Keldsen a.k.a. Dak"],
"w6my3nczlehkaddcw2ze4wi2":["dogfishcr.us","Dakotah Horace/32OrtonEdge32dh"],
"w52skkepvlmgrgrmyejqrxuf":["dogtwink","dakota 🚬🐕"],
"6gy6oianapr5vy4g5ir5kzre":["dogbark","Dakota "],
"rf7igocz2xn3j5culafili2o":["dpj","dakota"],
"7tgisqgiq2qgxziyjeyi2cgk":["drawkana","dak!"],
"5xqx6ysjzp6ndh6adqzyimdn":["draconicdak","Draconic Dak"],
"gvmp5vlkrbhix3lkkkcn7sjo":["dramama","dakahii"],
"vcpaybzbdo5wrdf67zbqbeyo":["dsides","dakota"],
"tlgjvku6yagrs2rpzubza5qm":["dsonoshee95","Dakota Sonoshee"],
"5f4jgq5kisl5gkxgx6secbxq":["duhxkota","dakota"],
"bw734b6kbwaklxol4q3altnz":["duckotah","dakotah"],
"yh6gyiwnqnd36cx5z4zno7bv":["duhkohtah","Dakota"],
"6hcdscxm3kvfxaavoyiqikrw":["echochvmber","Dakota"],
"kosx6ss6plk7aru47btxsmnl":["eldakak","Mohamed ElDakak"],
"yyvzy3titua76bk25cusrzmd":["epicureben","Ben Dakin"],
"skclo5u4u3xnueblwtvq7q54":["eugenedakin","Eugene Dakin"],
"xwlmw74eyjnpjwlcw2ezfype":["fabiodakota","Fabio Dakota"],
"rd7fug3h6335eawutdhwikpq":["fawkins","Dak Fawkins"],
"dvkhoucd53ywbs5cid6veuqs":["filledefeu77","Dakota "],
"ulra67qzj64s2w2zxy6beg56":["fluffandstuff","Fluff and Stuff (aka FurryDakimakura)"],
"ygtp4obr3mv2eg3jija3qmmy":["foxpirate","Foxpirate's Art 🌟Daku Con🌟"],
"zubuftktc7kj3wrvitlfnmky":["fragilis","Dakota 🦖"],
"qukwzrdqbiv7v5a4e3ep34md":["furrydakota","山猫 // Dakota"],
"d4ad7us54sz4kq4dfa7sklp7":["g2wolf","Dakota"],
"q7f6fb5njrsrayvmzivphit2":["galathir","Galathir Dakrstone"],
"l52uto6al7t2g4ahz32w5gp2":["gauntletgirl","MrsRenoDakota"],
"crj55bhqligu5sp6z6t4iib4":["glitzychu","Dakota"],
"4mi4y62kwx2vm5kdmakz2sw4":["glacierpeak","Dakobed, aka Glacier Peak"],
"k5o5iisalv5mq5excs3sqtvy":["gnarlybark","Dakotah the Slutty March Hare"],
"oe5s4mdoujez7o4qaimlujng":["h3dakota","H3Dakota"],
"wm2lddzdu5jmwxmuucvgeyw3":["haleysviaduct","Dakota"],
"suguumbjp7hfpe6vwuylfm76":["hedgiemunch","Dakota "],
"kmoj2i2ydsx73m6wu5gbjsc4":["highyeener","Dakaar 🔜 MFF 2023"],
"a52z7qihvboysy5v5432seq4":["himedere","Dakota"],
"yxhxbt6bhqbyjemxz3e3p6tj":["idakota","Dakota Joee "],
"2f6l7su3v5pykfdj4lzroto3":["impteenth","Dakota"],
"xzkhixsydirn6w4u47tqr4no":["imdakuro","dakuro"],
"ik4smy2jingwplvg3cqvxt32":["insaneclownpussy","Dak"],
"o4puuooyfjp5mz7m52vnrvpl":["ironicdaki","daki"],
"rnbqvhg63mnrrk4r7jbkiivh":["jdbo","Julian-Dakota Bock"],
"jgmnnfsco4sqqre6abzutvcz":["jesterful","Dakota"],
"tbdoo6vp7hu2phcxqi7hsjxo":["johanndm","Johann Dakitsch "],
"64y3vzajvudknwap3sl2zyax":["kayteedakun","Katlong Jonah Dakun"],
"7b27qw6we2ahvh6o76hbxu4i":["kaggy1","Dakota"],
"dceukcp2ppa5y2tsgy3rtoc6":["kingdakrios","King Dakrios"],
"u2c456n7mqv7spvt5p56mzey":["killingkota","Dakota"],
"mfmredxgbbf574apgqhe2zxq":["kingexe","dakota ✦ @ ace my beloved"],
"msct23i63fbjsylpitb5bnxf":["kingstwiggg","Dakota"],
"kg7z2fveaz77fpwi7ycktvzx":["kotatheblm","Dakota Blackstar | Carrd Comms Open"],
"44cn265hd645zbua7zw6mq7o":["krazyk0dak","Kodak :3"],
"a66i6vu42jumu7t2edypyvua":["layziidakkii","dakkii ☁️"],
"5zefwh5phqaxxrvafi5mpi3h":["leahfromsd","Leah from South Dakota"],
"lzvvun5s2elcrugg5zryt64i":["lokislittlefox","Dakota"],
"x3hqqwtlhae2za2x6k3yrydm":["maca5dakika","Maça 5 Dakika"],
"ofle7ndzxlzol472nws7b4pl":["maskofdakla","Dakla's hideout"],
"hsd4n2rtxo76flzcohsye6kp":["mettikandroid","Mettika 🔞 | Dakka Arc"],
"luq5dz5vsklkiiabpzvktumo":["mezkal-dakar","🍹Mezkal the Shaker🍹"],
"p3qytrrypq2f6dqfkxskh5iv":["meerfox","Dakarai Baarde "],
"ueqvmcxd3esomliwv7p6rwq2":["missdako","🌸 Dako 🌸"],
"xygw7k4qtd2t3csphaeqi3cs":["moonlittoxicity","Dakota Rosewald"],
"ov7yyu2taf5uzitjznhc2rto":["modakhilnba","Mo Dakhil"],
"y7s27kyovz5nxiwfi3h46vs7":["mothrum","Dakota"],
"lg2jpog7oel6defvskgfca4f":["mutetroop","❌ DAKKU 💀"],
"yx6ipyemc6md46jj5vxyqz4n":["nanoniall","Dakota"],
"yxjz4lqvpjnsyotfejfunot4":["nikosdakos","Nikos Dakos"],
"6ft3g67adpw4n44fn253krki":["nomadswandering","Dak Knomadd of NomadsWandering "],
"szhm6yf7arcxlaboll26xfrs":["nocturn3bud","Nocturn3: Deacon of Dakimakura"],
"nzixsjkocdmwl4z7a6j4evxd":["northdak.com","North Dak"],
"olctvl3iaeq6abm55ttysstu":["notthesongs","dakota"],
"isen3tvlydmvbp2mgbs6yzsb":["nudemothdakota","Dakota the Moth"],
"sdnequtmtvn36tyuywzlrdl2":["o1dakkun","🍋오닥쿤 ."],
"rrgfl33fhnvtbm5nhkod5kwg":["onetrueglob","Dakota"],
"mqol4kklqg3olvks4qhpjjsr":["oofermotorsports","dakota!!"],
"3mivavoiimxbnfox65srxwum":["ophedkker","Ophelia Dakker"],
"zxgjfdxhkh3kfdciwgj4vjtu":["parasaurpal","Dakota"],
"fk43yk2bn2cfphas3mxs2noo":["papascrumps","Dakota Dennis"],
"xvcxbjwwttluuiu3xwpkl7e7":["parsleycooking","Dakota"],
"o3t6hgbtwydoc4psg5jhs4ui":["princebaph","Prince Baph @ Daku Con"],
"qkpa5bmmvl4fy6lcb3chnpcd":["protodakka","Dakka // D4-K2A"],
"jpytze3iw5inmxyv6flbagbv":["pupdakota","Pup Dakota"],
"nnquimd5tch4sqiv7t2ykfzb":["quarterdak","QuarterDak"],
"325uqkjxjsgndfxchqg3mdrf":["rawrdakota","RawrDakota"],
"lmkyuch5uhelbynsd5ker7s6":["reallymccoy","Dakota McCoy, PhD"],
"dvs3orrc754ixvndmtnrgpkb":["renodakota","Reno Dakota"],
"u4zrcw6vgjjut5afh3o55obe":["rediragon","Tacoma “Red” Dakota"],
"euu6nrafv5ghwbjnfcdlgby3":["rexdakota","Rex Dakota "],
"2xhlmnqdpa7s3hkrc3xkzzdl":["reverenddak","The Reverend Dak of Ultimak"],
"3y4vqw6ubihmpgsdfirhwyzu":["rosearcanaeum","Dakota (they/them)"],
"lndvrtzaut2ubmtywgcyqpp5":["rootstosky","Matt Walton/Daka Sky"],
"yegsgc3rhpwjljp7neg6xfuf":["sdstate","South Dakota State University"],
"vgovzexa3z2h7ebow5binh53":["shinmaryuu","🧡🎃Slutty Dakota Costume🎃🖤"],
"kibno4ffb42mylzdoyizjjxc":["shadowtriad","dakota"],
"kwyqazhqu7deoj7wzeae2nxr":["sondakika","SON DAKİKA"],
"2vu6utmkypmmrylp6vnphdjs":["southdakota","South Dakota Department of Propaganda "],
"uqhieflhjuhtevjqaxsrezer":["sondakikahaber","Son Dakika"],
"pauh5sxufu3nov2okvexgkg5":["squareenix","Dakota"],
"5qbaoizlvuiap5visxiuvzwd":["steelwicker","Dakota R"],
"pgsxjclwcphrprvtdrmd2blg":["starrycosmic","dakota !"],
"5erqgzue44xym32omqcl2ptw":["teedotzee","Dakup TeeZed "],
"gkzozkxcvqsptjlsq5om34mv":["techpriestdakka","Tech-Priest Dakka"],
"kteu6jdaheygewr5by4wfctk":["thesamdakota","Sam Dakota"],
"gjabugofyh4rh5y4r45d4hna":["thekota","Dakota D"],
"6fxaai3ur73jlh4hcjcrpgge":["thedakota","Dakota"],
"6nua2gdo2wcoktlagc67i5pv":["thedakari","Dakari"],
"22cqazt52wxwvsvjmpd47t5w":["theleadershipguide","Cody Dakota Wooten, C.B.C."],
"fcp3pywh6sodcbazfy2d4lsg":["thesillyman","Dakota Sillyman"],
"dk6rsidvxor2y6qwkcvbv4u6":["thesrirachafem","Dak/Lily (that milfy twink)"],
"zphsn5sd4r46dxrokjcuv4xh":["tinykite","Dakota Sexton"],
"pqtrivzvct2bixlsruycgef7":["toxicmicroceleb","DakotaVAdams"],
"wsmhd2gqdwygs53fart63buu":["toxqa","Dakota | Toxqa"],
"fyudxjh6lxcmjxnk2upqfevp":["travisdakin","Travis Dakin"],
"gh3qftayeadcpnww65hveu43":["travisdakkan","Travis Dakkan"],
"2kkxnqyhqlahguedrglrvnad":["vaeifpx","Dakota!!!!"],
"vrb6vukjhfkkidc3vjss3nvt":["visioninlilac","Vision/Dakota"],
"wit2wbddqq224nigyzvm3flz":["violatorgirl","dakota"],
"eg6yzun72qmdyhia4hf365id":["volcanicdynamo","Dakota"],
"wigtrqqlp72ulbyqdxhklrei":["wakida","Dakiwa, NOT so busy."],
"qpmfojien6kq7ozc6466q2sy":["wagstail","Dakota 🌈"],
"f4smzf5gow7f5ih6ysdxi2pb":["weeniebagel","dak bagel"],
"vqtmvtxd5dkrrzjnztxscuuj":["xdnintendo","Dakota Southers "],
"elzfsfzmjalbccucvduha7nx":["xshadowxlinkx","Dakku~Boi"],
"4etmeyq64jalyhog33yov3ad":["xxdakotaxx","Pup Dakota "],
"bi5cbwd74q4ywya5y6hxfclw":["youdreamyrat","Daniel \"Dakinu\" Ferris"],
"nr23viix6d7pw7iyacjvue6w":["zekittyx3","Dakota"],
"flldjesbpgwzj557lio73oyg":"dakotadownunder",
"4yz7wgdfbj7ifhqzj6d6vt4h":"dakaila"
}
