{
"6urtn7yurynqucundm4mxh2r":["1c3b3rgmama","Mama’s Mojo Dojo Casa House"],
"kwblppycjqjhu7w5buwxryev":["akumanorobin","The Yiling Patriarch's Mojo Dojo Casa House 🇦🇷"],
"lak7jyazcqpcmollxezcw66h":["arikidojido","Arikitokurin Dojidotakashi"],
"n4ii76abeltokr6aeb4psjqv":["avarenity","avarenity @ Dragonstone dojo • they/them"],
"ohg6bbp6pp4neuzjbpf6bcvu":["bolodechurros","dojapobrete"],
"p54zvm3arefm7vitim5zndu3":["choekyi","George Doji"],
"ttuujeq35byhnzibuzlqapfc":["danhf","Dan’s Mojo Dojo Casa House"],
"enbckk6i2cfwpvxcji2dfjwt":["darkicedojo","Dojo"],
"54iobkpe4our6fsvoy5sn2hw":["dojacat","Doja Cat"],
"gusejb4hbm5tizdrottptvbz":["dojirudeer","Dojiru"],
"otsg3s55wga7u3bkfrh5dhb4":["dojimadeadlift","DojimaDeadlift"],
"smsuehelt45tj6cpmptvgwju":["dojo","Dolly"],
"xnzea7tp5sa6vdhm23w6zwi7":["dojimeme","Dragon of Dojimeme 🔞"],
"m3rfvq2piasdzvyykfk6g6bw":"dojao",
"wssv6ovnz52xoicyauotg73c":["dojalion","Gabriel 🏠"],
"us7zxy4s5btngsuxdg375zmc":["dojacis","lu."],
"kyvwxret5rfkceeeuj4lv2yb":["dojoe","DojoE"],
"4f7772vfqgqbvanl2eixk347":["doji","　　　　じんぼ なおし🍺"],
"syw4bp3mx32eyeueombasvy6":["dojobear","Winston Chow"],
"i6cubqbpyu6hgo25rnkd7qvw":["dojineko","dojineko"],
"dnjwh76ocrzlsok2nsyorput":"dojojin",
"7b77e4b4g6xotdzcth4opvgx":["dojisuave","DojiSuave"],
"e3lxynanz5gcro346dk2p6g3":["dojish","Dojish aka Seth Badbois"],
"wgbp4oqg2pqy25erckkuvzih":["dojyon","どじょん"],
"ksx2gcebccuz3uh4w5sdna3h":["dojoshibagaki","Dojo "],
"w6jioyv5roag7irkqbefhwea":["dojiii","Aline Viana"],
"lma4vspgu6hewc6lyvc7dxdo":["dojothegreat","Dojo"],
"tp3wsr6oqqu5ugzlhiddtmc4":["dojasring","gih"],
"v2nbkhvn5dme772xbntupeuv":"dojabolsonara",
"qduldji5qlnjb33wxxu25s5j":["dojiro","Dojiro"],
"kzdjgf27dfpy6yzu6jhgigmu":["dojagi","도자기"],
"xl62wiux6y4vqb554uvctzja":["dojulio","Júlio "],
"cfc22qt4p57bae7kuugslzza":["dojizerker","Doji | ドジ ⚔️🛡️"],
"j6qqw5mi3ops2f33m4xcz6yw":["dojoslapnuts","Dojo Slapnuts"],
"bda2yyte3rtmya3dxjyrhadz":["dojikkomeido","Meido"],
"s6q2oxhjyjjucslrh4idr37s":["dojae","yuer"],
"uvvgdcgr7fhigzj3zr5nftsw":"dojure",
"lcmmgy4vb5ika4bry4qkerdu":"dojumz",
"pwydlye32pininwub2aybbfa":["dojeong","도정쓰"],
"bl76wi4mt3j45ietu6rwj6dq":["dojavee","Dova Halloween edition 🎃 | $6.66 OF"],
"w6o22x7ttvcsahsmz4oxl2v5":"dojascat",
"a4vp3u24ombpsam6r7pqawow":["doj--ymst","깅정후"],
"3hua5lueqdemzshhviokd2pl":["dojjidi","dojjidi"],
"bsldsil2jtmufdrceaahiqq6":"dojakun01",
"wgclpws5dgefgidemvzhhczl":"dojodragon123",
"5o6ec2h3pyl47p27gck7dsm5":["dojindo","道人"],
"jjf7tgm3noex5dpzax2ip3uc":["dojafat","Doja Fat"],
"3folvxtakjspxgou3wstmtl4":["dojyan","doyj"],
"xs5ooyqimecd4c4yrw7oou3c":"dojeda",
"kzysto7wuk35itsjdh2a5d5s":["doj","water enjoyment goat/sheep"],
"f2lh6qmzl2qerwxy6kbkii4x":["dojang","どーやん"],
"oztxwkjk6jwhog6d57ol3cgx":["dojinx","Quinn"],
"jumk4xbg3w7qgltqibcb4evh":"dojarol",
"vmkv7mcugcu3mldvblb6imgm":["dojyaaanvon","Dojyaaan Von"],
"kewxwcooq7vwdocrwzo4auns":"doji66",
"akxbfaoxlvdgsb4jh66772xq":["dojaymi","DoJayMi"],
"xgntxiv6rekvrx6izczas4g5":["dojhavin","Javi M. García ✍️🎮"],
"gbj7sm5dtmx45ubfng2wrw64":"dojin",
"5jg7jrawq4ru53xlupm3mu7a":"dojno",
"egvbpqmu3fujmmriw3c6aqpa":["dungeondojo","DungeonDojo"],
"ml3ysdgm7qhqxs5gxfe67npz":["famicomdojo","Famicom Dojo"],
"3b3a3bk2abwkafsiyj4d7jqf":["goatpaste","Mojo Dojo Casa Hammi"],
"fh7hp3qtaoyyjb24ljmjm7v5":["grahseeya","anna is in her mojo dojo casa house"],
"4uaqhsbkizcxvcnlrvlzdsgc":["heinousberg","Doja Fat"],
"s7skmj5bppqpmryvg4ydbi43":["k1-nine","DojiKazu"],
"tzrhkcszdjaljfp4ohu5ar3g":["katialavida","doja kait"],
"l2znnmq3bedp3hkb7xnuqqs4":["koidojojapan","Koi Dojo Japan"],
"x45v7pb2kzhmzcpao6e3gysn":["letgons","doja let"],
"ig7npaqh6cf2xdrn6hw3aaly":["matesymazmorras","Mazmorra Dojo Casa House"],
"iscp4oso32kwzcd4tespl6wr":["masculinitydojo","Masculinity Dojo"],
"hsyhfgzbp4mh7uall345p3uh":["mihoquo","Mihoquo (Japanese Dojo by Matcha Samurai)"],
"ip5pca4thnl6x2bvlbyrexlp":["milesupshur","mojo dojo casa wilbur"],
"r4tpdqk3rpqjm53dkrgcujkk":["mr-mojo","mr. Mojo Dojo Casa House"],
"ixqujwjrskcdamwlsszvkexz":["mtdoji","Mt Doji"],
"fe5jnmg3b72shtotxgkagly3":["renakadoya","Rena \"The Dragon Maiden of Dojima\" Kadoya"],
"moirhpa4whrrbivywga4hfjn":["shenmuedojo","Shenmue Dojo"],
"5h24irsudnd6xu57y2ylrbd5":["soraharalov","🍷Ray's Mojo dojo casa house🍷"],
"o7appztf2o4daysvbq2v72mp":["spadeofnades","Cringe Lord Of Dojima"],
"5qehoxfmvcubq7djawwl4ibu":["spicydojo","Dojo Adjauni"],
"hx6s7ilpnezggh5sev7yjtzz":["supersad","Dojadog"],
"4dhdobw5akupkacycae5drru":["syteal","Syteal Celadon ~Shihan of the Digital Dojo~"],
"5deeyupascbdba5csvdaabrs":["thesociologists","The Sociologist's Dojo"],
"el56hnljlivalnvuxhfim2ae":["thimzsilva","mojo dojo thiago's house"],
"figud5nlhdiz52tykdka6pyk":["thedmd","The Dungeon Masters Dojo"],
"q4zl67b5nwohorw5jwh6wz3t":["thedojobrand","The Dojo Brand 道場"],
"ikhedc5oeqazj6lledc7n4k2":["videodojo","VideoDojo"],
"fno4cuchrmeow2zfoa6haj3r":["wnfcdojo","WNFC esports Dojo"]
}
