{
"47jzgw5ylwvwym2senumaluy":["dsyzdek","David Syzdek"],
"poojubtvegsajkxlpgawswuv":"dsyme",
"ov2tkzke6ag7jwawlvzmae5a":["dsynadinos","Damian Synadinos"],
"3op24c3tzon5smvpv3jskzqa":["dsybot","dsybot"],
"kharrrv75ka642xagg43ye7v":["dsy980716","김수영"],
"x3td52lbbk2hijtbj5hyaowy":["dsylm12","망고"],
"eqq2r7tx2vv2ngta24upuepv":"dsyntax",
"r3gvp4gn7vsjpoloq6ssanry":"dsy1973",
"op4x46v5qbiiagnk7tyzrszc":"dsynytska",
"ho73t2wvf55acokisy4gxav7":["dsyuuennb","KNY"],
"6xv3r5us535ptbdhtonzuj46":["dsy031","ゆds"],
"6jb4ss4bcfht5yk466fm3trr":"dsylexia",
"nb2hngtloqpzi3pbeaxaiwtn":["g0dsyndr0m3","Kite"]
}
