{
"2mibcyujqgucysxaxmuq55fm":["djdreamer","Dj Dreamer "],
"47vt2qgdd7bmeqkzo2wjvfrn":["djdarkfox","DJ Darkfox"],
"7lmqyz7qio6sohpytjwn7hnd":["djdumars","dj duMars"],
"cbhmruqcf5qvvxm3nf7kpudg":["djdwight","djdwight"],
"dr4hhg363fqx6zpzcukl6uib":["djdunclive","Festive Autumnal Mr. Grift"],
"hbmvafh7ep3yc3n3lom7dxt3":["djdlddu","군군"],
"hodr3yn3jc33hxme4hzjjkvn":"djdesign",
"hzraooiahu5f752s7iywlvkw":["djdoogie","DJDoogie"],
"m6fny2vkg3wp2vb2lhayqgvn":["djdrchef","DJ Dr Chef"],
"ncl7rtfbl6mrbk2vkb65haft":["djdrjoe","DJdrJoe"],
"p5pyz3yoac76lqqnhuqycyup":["djdynamicnc","DJDynamicNC (he/him)"],
"r5z7mh7nhzg5tjemcf7ryr7e":["djdistemper","THE TASTEMAKER"],
"rhi2pdue3vuwhdmbhcl4fs6o":["djdiem","diem"],
"odocszzlu5uebg37hjnavzy6":["djdoherty","D. J. Doherty"],
"zb2apmj42uxqutooafn6ry3a":["djdabs","djdabs"],
"ihnrk4w2mk4pftzq36zghhmw":["djd","Doug Davis"],
"vinwbbal24aspp4q53ahvxkm":"djdmbrwsk",
"ixsf7ukbfk7rkf54hsejkuq4":["djdiandrade","Di Andrade"],
"pw7d6uhudnymumo5bppk6mn7":"djdewitt",
"vdzi47yomeh7qv6jc5dpea36":["djdanmurphy","DJ Dan Murphy"],
"hq2dzh2abybxjnqk4cssbhwc":"djdubd",
"qksxd5zg3cnckyrkpczmkpvb":"djda",
"ke7aqnp54djio7pzd3ybdoeb":["djmidori","djdjdj31"],
"p4akp2gqjztza2irfx5tunw3":["djdig","Danielle Kempe "],
"bacsjmxirh7spcuzka6h3sw7":["djdtb","드랍"],
"muxqsfruhfq6pa3jzvhqr743":["djdarkrai10","Dj"],
"ju6mbwmxyovhugjq4gdzpazc":["djdozamd","DJ Doza"],
"bzk2st323k6xqfja3ydmk2oc":"djdaskeleton",
"5v7nydxx5syyjdtyrzgnee3l":["djdaem0n","DaemØn"],
"fcy6xvnsl7w4ljfqljjkyogu":["djdragonfire12","Nero"],
"i7vam6ghzij4wikvs4grpbk6":"djdresden",
"npvxthkpqdoklxu3xzn5wirt":"djdan",
"av5seq3ql4nbosdgmp2wwoa6":["djdague","David James"],
"qa52b5iphdij27ngx6ptsusj":["djdekimasen.online","DJできません"],
"wbicncrxgtavhgl7wiamdra2":["djdeanrelax","Dean Relax"],
"hilvq2gjxxouxacscqlqr5o2":"djduster",
"7p37spk2uhlghcxyczl4vjqd":["djdevin","[object Object]"],
"l6pmfumbbwn4nnbeunbx3khj":["djdiscobot","Lizmet (allegedly)"],
"wv3krlphgp6lrv2u53wklwcq":"djdanl",
"uqxl6kftvdx7cwn5r4oq3arb":"djdanielnieto",
"qspgpex3ujfloqq4w7xgso4k":"djdeepdish",
"ahyylpmio562sovi4ydpykxy":["djdev.me","Dj"],
"zgiyme4xu6pq2nq5opcivrt5":"djdowney",
"ljcadgcdk6wbwhnamr2flpur":"djdonatas",
"2aj3lppo2ywfyiyoct7vaccv":"djdragonfly",
"gx57ahwtn2l6eva6jtgtxil5":["djdw","DJDW"],
"v72lig5jxd4oqwcru7yszncy":["djdadfucker","iridiana"],
"ejirqjw4wep4vusual6h3u73":["djdavid98.art","DJDavid98"],
"3w7rxmsesc2uk7poqqg6juw2":"djdave",
"hul7behlmbpupkdeppftqyg2":"djdaymos",
"jxfqspwplnk7ueo6rt2pvph3":["djdaddy","DJD"],
"sgsgfuht644pt43og2vzfwmm":"djdarkbeat",
"izq27ru7wt5cafc2dmoratdk":["djdjponi","DJDJ"],
"hsfurxckpas4qxychgsmtwsz":["djdekoning","DJ de Koning"],
"ftrem5nvzjrbwaozjdi5wk3o":["djdoc","J 2 tha izzo"],
"uhazgbnt3opwppwvg2lju4lk":["djdjpump","삼브녀"],
"4zuimrrgsa4zguyltwwvh7gq":"djdilla",
"6x5ccf2i5k3dkqqbepnk2ga4":["djdonatsu","DJ Donatsu"],
"q4fc7skln7sl6x2ro6zwb2wd":["djdarkside","DJDarkside"],
"syyinsbiwyfl55swenhed5tp":"djdoodle",
"ytttoh7et6drae5vklwz3dz6":["djddj","🎃"],
"rfsypt6uopvl5sdvlbhyo7ts":"djdj",
"an2ejp24vrhzj4fkrrvdsuam":"djdyingturkey18",
"cr5gfkoyqvg3mb2uo7lzpvkv":"djdecompose",
"7fot66ge6qsrrtfpsizh2nmb":["djdonut","DJ Donut"],
"tnhcnbaymv6j7jngr5oif5rj":["djdapperdan","Chris DJ Dapper Dan Brown"],
"fp7pdaktg34xtibixtksnftj":["djdubow","Dixon Dubow  🔜 PAX Unplugged"],
"7dn2glweze7k2ascingaw6q3":["djdovex","DonavanDaBirb "],
"bzzrboyyxcomwyxxwdon4vek":["djdiamond","DJ Diamond"],
"2ptlo5suy77wtefrplo5b7vq":"djduffy",
"ds2opnu5qr6fg3zsuwk3f5ul":["djdracula","Dracula 🏳️‍🌈💖💜💙"],
"q3fl3j2px4yabgtpkarm5mfo":["djdray17","DJ Dray"],
"m7h6lo4cikanw37rupenokdx":["djdjd","DJ Davis"],
"vmji7you4r5xu6v4tydyz7l7":["djdthtrp","「D.J.」◁ ワァー。"],
"mts6yqlyjzdvd7jypby4noo6":["djdono","Donovan Fehr "],
"bsvz3qc4i7agy7b26vyfbenr":["djdreamer56","DJDreamer"],
"kvcnljjuxnnbyhu4zo4dt5sq":"djdiamond3860",
"v7x52isg7rod3kwkogy47ils":"djdugan",
"zyfijxxdcakjecwytjvn75yi":"djdoranem",
"dinxbqpvq7tj6idkvuwh6alb":"djdjekkc",
"wjpggqv5vyrvgsfesfn43u6v":["djdega","DJ Dega"],
"c5yc5nl7pldhsyy4eyej3iwq":["djdiver","DJ Diver"],
"vpackd6rhjh6onsjjkv3mfmi":["djdatch","DJ datch"],
"i54iyvrqrcgwrbl32s2ms6ec":["djdavidtimothy","David Timothy"],
"2gjnwhqxcpwgtxep7xqs5776":["djdinkel","DJ Dinkel"],
"bvdmegopsqawaxl55bdrnqhc":"djdhfkske",
"rpn66rg33rdwcl2poffmkw42":["djds","DJ DS"],
"ppq46xf4dybjotilrr7cwtn3":["djdavidson","Donald J. Davidson"],
"uz4oqefn2bmgnzhtyqazwhho":["djdollipop","Dollipop"],
"vzdnc3zpnjsgoo5zgbuhckog":["missispoi","Djdebs"]
}
