{
"ev7sfhb7u274sjjmaxuhvvqk":["actuallydjs","I am Actually DJS"],
"2wb2gaophxbrhdrnyrdvkmbf":["djsmithers","DJ Smithers"],
"36louqgw5qk7fdn7my4yzaq2":["djsabrina","DJ Sabrina The Teenage DJ"],
"6iykdnhns6e3ip4jwkdngnjp":["djsalad","Hog Washer"],
"76zux5ytuota2najwcsrwphk":["djslapchop","avianna"],
"aapxe5gg3otmpoiqw2svcwtz":["djshort","D.J. Short"],
"c3qnp2nx3forqolvuddptqof":["djsqwrl","DJ SQWRL"],
"c4wgsrw7xgedmal2rdliamwn":["djstrap","DJStrap"],
"coqcz57mibhgdmpcszllub45":["djswolfuk","Swolf"],
"dozn6tm7e3iuhqds5k2angxl":["djstarsage","DJ Starsage"],
"fx2nto2buuthck6opdljthuh":["djshackson","Dave Shackson 🇦🇺🏴󠁧󠁢󠁷󠁬󠁳󠁿🇺🇦"],
"hoqurpovlwba4etknvusfcfg":["djsmokingban","eoghan"],
"i7p5cbx5vpg2h2y7l2mi7c7h":["djstonecox","STONE COX 🐶💿🎚️💿"],
"iwplwcdytb5bnw6cno7wkzj7":["djsoubise","resting kitsch face"],
"jwke4qcwod5evudifxhicne6":["djscandal","Good ole DJ Scandal/Timothy"],
"nbpvp7dg4j7bdtjsj3sprj4j":["djshire","Shire"],
"o6o2u2byc2cellhzzisujort":["djsziff","David Ziff"],
"ohozzheujxxu7marcqggif6x":["djskelton","David Skelton "],
"prfwa26ea2ranfioczb2hu2o":["djstormageddon","Matt Storm aka Stormageddon "],
"qjuop5buthbcr53afvytkeat":["djskraps","DjSkraps"],
"tlzomkrg7t7dceyjis2nzwu3":["djstangl","Dennis Stangl"],
"tt6xj6rmv26jv5yplowmqe2p":["djstarion.com","dj starion (windows 98 enthusiast)"],
"v2saa7dgg427hdv4qbqi7lgh":["djsammyp","dj sammy p"],
"wdwnlbonxjwpem3edvcuovhi":["djshere","DJ"],
"zvx4i7lwp2rrwayodfi7rqnd":["djstarrnoir","Starr Noir"],
"jwvgz3jonwnrtk33y3od3i7u":"djstickyboots",
"o5ztcozn2ssuu2jgabic2nuw":["djscrew","DJ ZABAGLIONE"],
"ztoekl2qw2qg4rbmq2lhlkpe":["djs","Danielle"],
"ukbrzssthubmbqw7b5m6znsv":["djsflm","dieunJoynder"],
"3ujj6jkda7wh34qhxnupsiuq":["djsteviespins","Stephen"],
"ud7inijsrt2yyly26mwrbytb":"djscottyfox",
"z2tpdm433p3lfjasqjc2e3ii":"djspohn",
"zuddhk7vlinxj3374rzcv7p5":["djsoke","Dj"],
"lajzs2ee7gn4lxams5xyzli7":"djslizzard",
"vjd7g4m2hbrbzuo23kej7k2e":"djscream3",
"m5eyb52mk35f2fgtfk7mcg7y":"djshan",
"4osbh2t4pvovtp33jgixbya3":"djs21",
"5er2sjmm4c7nosn7pgr3xqof":["djsiren","DJ Siren"],
"5pxqzrc7hzsldqpek5bjzf76":"djstella",
"teohi6xykttw74bogn6snj5l":["djsoju","moan chomsky"],
"qnujzbkvt5g7x5beqdaxc57c":["djsimon","Satoshi Simon TAGUCHI"],
"iuhkbaniunzmn25hlzv45uyb":["djscruggs","DJ"],
"s5xlqxsjaeb2wgcrskg4uyc4":["djscope","Igor Rebenko"],
"365cmyunsyxqxdk4i4deenvy":"djstrongstyle",
"zabuav5thl3i7ybduckxfqoc":"djsteinmetz",
"jfhm7zd5fnuuawukgkokjld4":["djstinky","DJ Stinky"],
"fzisiid56al3w4pkrapdx6dg":["djshield","James Shield "],
"a5qvgchumfau2ulddzfcixdu":["djsuzib","DJ Suzi B"],
"p4m5mlb4fqsoxyopcydc3u3j":"djslamcock",
"gxbf3dmaeo2m7lfgpvk6duha":["djschwin","@djschwin"],
"tpv7yfu6vgnev5yl2d7j6ds5":["djsnow","Dust Snow"],
"gqre3g6iz3fngex5gcgue3xj":"djshey",
"wnbnmixxhcgyovzxeaysfyv4":["djsteppo","DJ Steppo "],
"qu2oyrl4lkw2oxgb6w5xp2jj":["djsalinger","dj_salinger"],
"psu4cgbmwtdgdaambntaaulv":["djsjdjsjdjsj","катруся🇺🇦"],
"z4fohycselpnsd7tsyrhtxrm":["djsleepyspice","Briana 💕"],
"flha4u4dy4zht4iq3glwhzo4":["djscias","DJScias"],
"qynrod7hurxn4zesmryfvk5e":"djs1914",
"bptfzfeqey2xxnkljte6i4yq":["djstephaniebell","Stephanie"],
"civlov7eimzaolssvujbp3nx":["djskout","DJ Skout"],
"dhry7w7ie3anreyt4aohjlkm":["djsalmon","Sponch"],
"gfbfnuwnd66blgcjtz3d7bbq":["djsev","S. Justin Poirot"],
"wxejhwxqlp4jxvpu5qbsicgk":["djsaria","SARIA @ Neonya!! Party HARD SOUND HALLOWEEN 3 10/11"],
"nemkpmr6nx4lwhcu7ehajpxm":["djspookyty","Tyler Johnson 🥕🐶🐶"],
"msucdb3b6avftgvi4nkira2v":["djsodacat","DJSodaCat 🔜 MFF"],
"wglooert76rahcvzufdlnfmi":"djsirsilviapa3",
"7cn5r5ef2vqdzytfbuwlpelx":["djstrawberry","🍓"],
"54fkxn7afdpbslvaptnfgmtm":["djsd","Just Another Michigan Man"],
"psse2qf3gxi4shtmlw7ua7qk":["djstygian","DJ STYGIAN"],
"utb56ibpl3mbxruzper7xk4c":"djsmith",
"kv7fow4mavfksrk3myba3xvc":["djslo","D"],
"5bfbl3gh2jnk73xfeme5hike":"djstino",
"uqwrratxy44qrhb3cfnuanjj":["djscusa","Djscusa"],
"nlmpb3am7blavfakyctjmlpw":["djsnowy","Snowy"],
"gu3f5jq5ukoye5ujx3fmytse":["djsteveporter","DJ Steve Porter"],
"vfpfc5k5cqb3zatllzylvgfj":"djsipe",
"mrcqzle3rzeaz6bjbshjsspm":["djschoolpizza","DJ Chainsaw Man Was Good This Week"],
"ihtlihegdbe4oc6253f42uei":["djsacc","Y Konno"],
"vvnwi2zzmlpi33agaxgaskvd":"djshannon",
"twhhvuiw2hlh7vjsjf4qwbuu":["djsteamypete","Peter Gillette"],
"6y5jnt27vprlckgorjt4k55d":"djsojus",
"v6jhpv47sn5cg3ubbzk4g374":["djshistorian","Daniel Sherman"],
"un6zayixheew22irsb56ytvt":"djstampy",
"jdjkww6j25vj2qnfec3airsl":"djspencer",
"5de75vmx62folkjcxiuifp3b":["djstiltecoupe","DJ Stiltecoupé"],
"lm5a6oni3l7yaaukdcy7m7vy":["djsylveon","DJ Sylveon "],
"7dmkugspqkqljvnflv67sumr":["djsardine","Alex "],
"bzywrazvzr6juoxqr5rgafpz":"djshortshorts",
"a42n5m3i2zs4e2bnsryuicy5":["djsmallz","DJ Smallz"],
"xdm6sysy3tvyf6yhyfyurg7b":"djsz",
"x65xoywdqnbd7lyslhti7d4k":["djselecta","Dj Selecta "],
"i6cebnjywdadcnx6dtuemy4t":["djspeednwa","DJ Speed"],
"ibjrrfwixtyxneseceujjqj5":"djspineboy",
"yamkjnnx6b7ttgroqobpb4jd":"djshakechilli",
"jr54pjegvfy3oiuscgspzeog":["djsimmons","Daniel Simmons"],
"fy3kdhdwk7wf2f4hfuhpilh6":["djsoliloquy","djsoliloquy"],
"gj74ainszy5cj2ib6b24gqcm":["djscheddar","DJSCheddar"],
"n3w55aali4wi4ind4v6wd4cm":["djsb","어뉴"],
"g3lc4gufzxqaci5stpfv3twy":"djschexmix",
"6hu3fk7ztbi2g6bgzakywvwh":["djsredanovic","Djordje Sredanovic"],
"edqdgrz3r7knpa3t2xotng36":"djsnj20",
"p7lkqorptdqzslal2p25jimb":"djsturt",
"lzgq57oueixq55yikayobs6z":["djsluss","Denise"],
"3kka3vnv4cph22lquu37dyc6":["djsarchivist","David Johnston-Smith"],
"ij3dcavnpgnl7wc3keouwo5m":["djsensei","Dan Morris"],
"bzmjm2fmfzokrwyaybwi4bij":["djstarsaber","Star Saber"],
"kint7fazlqbic7rmtmxojyjm":["djspapa","Derek"],
"oyru7mn72x4wnia24q4jd44t":["djsamo","djsamo"],
"7qtqumrw4lyerj7h46nszb43":["djsmallchange","djsmallchange"],
"3ehbbxirjp2wo5ywgz2npvqa":"djsbsjchs",
"l2arzhxd4d7ol2u6ujuqz4qf":["djsolarswing","DJ SolarSwing"],
"u65zrdcjqs4sha2lizldcs4s":["djsamples","Ben Samples"],
"hqxo64ty25mzzahhhgkfyhhi":"djsnowman3",
"o7fxh4i53ymrlue6jkx7rsmu":["djsnappers","Kait"],
"lprr5hskbebdi23wlj7euxqr":["djsalaryman","DJ_Salaryman"],
"k7yalmcqgfua6lgxqaza4bg6":"djsacrilicious",
"5flu23idnn7kabtijw2kcklc":["djsonicgo","DJsonicgo"],
"xkhpz5su4752mrc6udjuxz6e":["djstrummer","DJ  aka Electric Jethro"],
"zazafgmkz3lj2aampgjbg3ld":"djsirsilviapa0",
"klvxrzmwergcl7ixgumlzzlp":"djspuddy",
"xu7sggr5w7sqw2il2hs3b6cu":"djsinnimin",
"lv7taksjcs2vprghstsg42q6":["djsparks","DJ Sparks"],
"keqvsef4jx33ac3ldkbszhju":"djscram",
"nd356knpwlma3hnay7vajec7":["djsmile06","Smile ♤🃏"],
"2oep5njg7utozrtah27ndtqb":["djsatsuki.com","DJ 五月"],
"ohxxgq2r667bdp7lr5vpnisy":"djsooz",
"aa4xupnziqdn3wm3eftiuyn2":["djstar323","Djstar323"],
"ulesy4yhflgwoxyvejcnzawc":["djsnoopy","🔗"],
"lram7mdhqs5wdpupo7wqkoah":["djstarionsfw","Francisco (NSFW account)🔞"],
"s4ytthppxrtwy5ss72fdpjj7":["djs642","Dom Sanetick"],
"xle3a7ewhhate3zlqn77draj":"djscruffy",
"47cr4jdhi2d7v3rqufulme3r":["djsoftcrush","fish collision"],
"tra4d4x25atxqkdlnucvkng7":"djsnowman24",
"dbl3a66gtmrkyefmnogjlswk":"djsandeman",
"jiyvbhfzkgsaqrwmuoiapcmk":["djserdarsahin","Dj Serdar Şahin"],
"4hlgonjmt3czzfrzhdmlibeq":"djskywalker",
"tss2zfmhev23257f22qymfrq":["djsammyd","DJSammyD"],
"36pyipafqt6hjclhn43u7akz":["djsflsdudn57","월야"],
"5ozpqtyo7iieeo6vangdtqb3":["djserjaysvek","Serjay Svek 🌈🏄‍♂️ UNDERTONES"],
"ksw6g67hixlgalnkvigsnwdg":["djshark","DJ Sharkowski "],
"o2p46khejkhywuqoqn6f5awu":["djsarthur","Pixel Artificiel"],
"zgdtzvarhr5vuh5ey7unhh6c":["djshepherd","DJ Shepherd"],
"mzpacojunriln5knmw4syteu":["djswitchpdx","DJ Switch PDX"],
"mzrddlgyzo3m7dysa4sgmnys":["djshortround","ShortRound "],
"zgcrlq2s7wb2bjs5wgbb5vw4":"djspearman",
"bz5bqqj6ykbes332g4eggg5t":["djsfreshfadez","Damon Johnson"],
"cg4klgpcwuzyiqaq73jkrntq":"djsackboy2",
"hdd7tsb32wxt7qephq5qr5gw":"djsaturn",
"kgjpebm4lrk4wgg53zj2sgp2":"djsaesch",
"vxelf265ivhustmxri4gkznu":["djspiteful","Alastair Stewart"],
"4hqggtem6xtami73qfix5p4j":["djsheatl","DJane Sheatle"],
"235kmil5eqyk3stt2zr6exny":["djsanity123456","Gabrihell Lima"],
"gphzdwa563rnfhczqmdpxdfk":["djsaintu","Darren Saint-Ulysse"],
"evvelefvuejokwbcu6j7w666":["djsideshow","Shane Lei Graviss \"Dj Sideshow\""],
"vqirbk6wzp7mmrzmhkjh6zip":"djszusjwbs",
"mj4znyc6oom7y3o3ddcrn2he":["djsparksldn","Mark Williams "],
"73p62l2w5opix54t6mzfbz75":["djsudoku","DJ suDOKu"],
"wptdsl4jwpjg5uye6k5xawaz":"djspottie",
"z7mt6hccbdbopszd5zedwgxh":["djsellersauthor","Daniel Sellers"],
"wtsfzdl43p2n4ud2wwqar7b5":"djstanard",
"tmo46kk73i752csrcv4izpij":["djs-jds","DJS JDS"],
"6zwo2gv5qxqt55rxrz4socjc":["erin-p","1000 Lesbo DJs"],
"53sa34wrn7xplm3gmbr3tpdu":["fuzzboxdjs","Fuzzbox DJs"],
"rcu6f7twiqhfqs6zf3hs227m":["sdds","djsdds"],
"mbpqt5nsltkvucibqjnnqbze":["seismicsound","Seismic Sound Djs"],
"7khfff7iedcwkfczourson5s":["sushipolice","DJSP🍣🚨"],
"fkqkwbrgzhhdyv5wwifiycby":"djspringbreak"
}
